async_substrate_interface/__init__.py
async_substrate_interface/async_substrate.py
async_substrate_interface/const.py
async_substrate_interface/errors.py
async_substrate_interface/protocols.py
async_substrate_interface/substrate_addons.py
async_substrate_interface/sync_substrate.py
async_substrate_interface/type_registry.py
async_substrate_interface/types.py
async_substrate_interface/utils/__init__.py
async_substrate_interface/utils/cache.py
async_substrate_interface/utils/decoding.py
async_substrate_interface/utils/hasher.py
async_substrate_interface/utils/storage.py
async_substrate_interface-1.5.15.dist-info/LICENSE
async_substrate_interface-1.5.15.dist-info/METADATA
async_substrate_interface-1.5.15.dist-info/WHEEL
async_substrate_interface-1.5.15.dist-info/top_level.txt
async_substrate_interface-1.5.15.dist-info/RECORD
