Metadata-Version: 2.1
Name: async-substrate-interface
Version: 1.5.15
Summary: Asyncio library for interacting with substrate. Mostly API-compatible with py-substrate-interface
Author: Opentensor Foundation
Author-email: BD Himes <b@latent.to>
Maintainer: Latent Holdings
Maintainer-email: BD Himes <b@latent.to>
License: MIT License
Project-URL: Repository, https://github.com/opentensor/async-substrate-interface/
Keywords: substrate,development,bittensor
Classifier: Development Status :: 5 - Production/Stable
Classifier: Intended Audience :: Developers
Classifier: Topic :: Software Development :: Libraries
Classifier: License :: OSI Approved :: MIT License
Classifier: Programming Language :: Python :: 3
Classifier: Programming Language :: Python :: 3.9
Classifier: Programming Language :: Python :: 3.10
Classifier: Programming Language :: Python :: 3.11
Classifier: Programming Language :: Python :: 3.12
Classifier: Programming Language :: Python :: 3 :: Only
Requires-Python: <3.15,>=3.9
License-File: LICENSE
Requires-Dist: wheel
Requires-Dist: bt-decode==v0.8.0
Requires-Dist: scalecodec~=1.2.11
Requires-Dist: websockets>=14.1
Requires-Dist: xxhash
Requires-Dist: aiosqlite<1.0.0,>=0.21.0
Provides-Extra: dev
Requires-Dist: bittensor; extra == "dev"
Requires-Dist: pytest==8.3.5; extra == "dev"
Requires-Dist: pytest-asyncio==0.26.0; extra == "dev"
Requires-Dist: pytest-mock==3.14.0; extra == "dev"
Requires-Dist: pytest-split==0.10.0; extra == "dev"
Requires-Dist: pytest-xdist==3.6.1; extra == "dev"
Requires-Dist: pytest-rerunfailures==10.2; extra == "dev"
Requires-Dist: bittensor-wallet>=4.0.0; extra == "dev"
Requires-Dist: pytest-forked; extra == "dev"
